sonocrop/__init__.py
sonocrop/__version__.py
sonocrop/cli.py
sonocrop/vid.py
sonocrop-0.56.dist-info/LICENSE.txt
sonocrop-0.56.dist-info/METADATA
sonocrop-0.56.dist-info/WHEEL
sonocrop-0.56.dist-info/entry_points.txt
sonocrop-0.56.dist-info/top_level.txt
sonocrop-0.56.dist-info/RECORD
